{"charging_status": {"country": "United States", "city": "Oceanside", "purpose": "PERSONAL", "power_kw_display": "0.00", "is_purpose_finalized": true, "update_period": 8000, "utility": {"plans": [{"code": "EV-TOU-5-NEM3", "name": "Domestic - Cost-Based, Time of Use, Electric Vehicles (NEM 3.0)", "id": 3436794, "is_ev_plan": true}], "name": "Clean Energy Alliance", "id": 101204}, "lon": -117.3271713256836, "power_kw": 0.0, "session_time": 4137000, "has_charging_receipt": false, "payment_completed": true, "energy_kwh": 3.9114, "total_amount_to_user": 0.0, "device_name": "CP HOME / 214541061163", "api_flag": false, "outlet_number": 1, "state_name": "California", "organization_currency": "USD", "pricing_spec_id": 0, "currency_iso_code": "USD", "current_charging": "done", "lat": 33.246150970458984, "vehicle_info": {"year": 2021, "ev_range": 200, "is_primary_vehicle": true, "model": "XC40 Recharge", "battery_capacity": 78.0, "vehicle_id": 21847141, "make": "Volvo"}, "port_level": 2, "charging_time": 1586000, "device_id": 12048111, "company_id": 12967, "is_home_charger": true, "address1": "Home Charger", "end_time": 1767563917000, "energy_kwh_display": "3.9114", "session_id": 4740843051, "update_data": [{"energy_kwh": 0.0, "power_kw": 0.0, "timestamp": 1767559778000}, {"energy_kwh": 0.0, "power_kw": 0.0, "timestamp": 1767559784000}, {"energy_kwh": 0.0001, "power_kw": 0.309, "timestamp": 1767559788000}, {"energy_kwh": 0.0229, "power_kw": 9.0294, "timestamp": 1767559800000}, {"energy_kwh": 0.0727, "power_kw": 8.9966, "timestamp": 1767559823000}, {"energy_kwh": 0.1969, "power_kw": 8.9901, "timestamp": 1767559872000}, {"energy_kwh": 0.7056, "power_kw": 8.9717, "timestamp": 1767560079000}, {"energy_kwh": 1.4488, "power_kw": 8.9624, "timestamp": 1767560379000}, {"energy_kwh": 2.1919, "power_kw": 8.9766, "timestamp": 1767560679000}, {"energy_kwh": 2.9343, "power_kw": 8.9382, "timestamp": 1767560979000}, {"energy_kwh": 3.6759, "power_kw": 8.9697, "timestamp": 1767561279000}, {"energy_kwh": 3.8957, "power_kw": 8.9477, "timestamp": 1767561366000}, {"energy_kwh": 3.8957, "power_kw": 0.0, "timestamp": 1767561579000}, {"energy_kwh": 3.8957, "power_kw": 0.0, "timestamp": 1767561878000}, {"energy_kwh": 3.8957, "power_kw": 0.0, "timestamp": 1767562179000}, {"energy_kwh": 3.8957, "power_kw": 0.0, "timestamp": 1767562479000}, {"energy_kwh": 3.8957, "power_kw": 0.0, "timestamp": 1767562779000}, {"energy_kwh": 3.8957, "power_kw": 0.0, "timestamp": 1767563079000}, {"energy_kwh": 3.8957, "power_kw": 0.0, "timestamp": 1767563380000}, {"energy_kwh": 3.8957, "power_kw": 0.0, "timestamp": 1767563680000}, {"energy_kwh": 3.9114, "power_kw": 0.0, "timestamp": 1767563917000}, {"energy_kwh": 3.9114, "power_kw": 0.0, "update_date": 1767563943329, "timestamp": 1767563917000}, {"energy_kwh": 3.9114, "power_kw": 0.0, "timestamp": 1767563917000}], "has_utility_info": true, "zipcode": "92058", "last_update_data_timestamp": 1767563917000, "start_time": 1767559778000, "payment_type": "none", "total_amount": 0.34, "billing_time": 1767563918000, "company_name": "CP Home", "start_offset": -28800, "miles_added": 10.02923076923077, "stop_charge_supported": true}}